pyspring/__init__.py
pyspring/mastermind.py
pyspring/mastery.py
pyspring/palindrome.py
pyspring-0.0.2.dist-info/LICENSE
pyspring-0.0.2.dist-info/METADATA
pyspring-0.0.2.dist-info/WHEEL
pyspring-0.0.2.dist-info/top_level.txt
pyspring-0.0.2.dist-info/RECORD
